pyconnpg/__init__.py
pyconnpg/connection.py
pyconnpg-1.4.3.dist-info/METADATA
pyconnpg-1.4.3.dist-info/WHEEL
pyconnpg-1.4.3.dist-info/top_level.txt
pyconnpg-1.4.3.dist-info/RECORD
