Metadata-Version: 2.4
Name: pyconnpg
Version: 1.4.3
Summary: A simplified Python library for PostgreSQL CRUD operations.
Author-email: Josephus <orca099210@gmail.com>
License-Expression: MIT
Keywords: postgresql,database,connection
Requires-Python: >=3.10
Requires-Dist: psycopg2
Requires-Dist: cryptography
Requires-Dist: dotenv
